odoo8_addon_web_tree_many2one_clickable-8.0.1.0.0.99.dev3-py2.7-nspkg.pth
odoo8_addon_web_tree_many2one_clickable-8.0.1.0.0.99.dev3.dist-info/METADATA
odoo8_addon_web_tree_many2one_clickable-8.0.1.0.0.99.dev3.dist-info/RECORD
odoo8_addon_web_tree_many2one_clickable-8.0.1.0.0.99.dev3.dist-info/WHEEL
odoo8_addon_web_tree_many2one_clickable-8.0.1.0.0.99.dev3.dist-info/namespace_packages.txt
odoo8_addon_web_tree_many2one_clickable-8.0.1.0.0.99.dev3.dist-info/top_level.txt
odoo_addons/web_tree_many2one_clickable/README.rst
odoo_addons/web_tree_many2one_clickable/__init__.py
odoo_addons/web_tree_many2one_clickable/__openerp__.py
odoo_addons/web_tree_many2one_clickable/i18n/web_tree_many2one_clickable.pot
odoo_addons/web_tree_many2one_clickable/static/description/icon.png
odoo_addons/web_tree_many2one_clickable/static/src/js/web_tree_many2one_clickable.js
odoo_addons/web_tree_many2one_clickable/views/asset.xml
